fixed_width_int.py
fixed_width_int-0.1.0a2.dist-info/licenses/LICENSE
fixed_width_int-0.1.0a2.dist-info/METADATA
fixed_width_int-0.1.0a2.dist-info/WHEEL
fixed_width_int-0.1.0a2.dist-info/top_level.txt
fixed_width_int-0.1.0a2.dist-info/RECORD
