Metadata-Version: 2.4
Name: fixed-width-int
Version: 0.1.0a2
Summary: A robust implementation of fixed-width integers in Python that precisely emulates C-style behavior.
Author-email: Jifeng Wu <jifengwu2k@gmail.com>
License-Expression: MIT
Project-URL: Homepage, https://github.com/jifengwu2k/fixed-width-int
Project-URL: Bug Tracker, https://github.com/jifengwu2k/fixed-width-int/issues
Classifier: Programming Language :: Python :: 2
Classifier: Programming Language :: Python :: 3
Classifier: Operating System :: OS Independent
Requires-Python: >=2
License-File: LICENSE
Requires-Dist: six
Requires-Dist: typing; python_version < "3.5"
Dynamic: license-file
